<!-- German de-DE (© Revan ©) -->

<Root>
	<Entry>
		<zType/>
		<de-DE/>
	</Entry>
	 <!-- audio options menu text -->
	<Entry>
		<zType>TEXT_MUSIC_TRACK_DISABLED__USER_SKIPPED</zType>
		<de-DE>Track disabled (Marked as skippable by you)</de-DE>
	</Entry>
	<Entry>
		<zType>TEXT_MUSIC_TRACK_DISABLED__IS_NOT_MENU_MUSIC</zType>
		<de-DE>Track disabled (Only menu tracks allowed in menu screen)</de-DE>
	</Entry>
	<Entry>
		<zType>TEXT_MUSIC_TRACK_DISABLED__BY_MUSIC_SYSTEM</zType>
		<de-DE>Track disabled (Licensed track is disabled, or, another reason)</de-DE>
	</Entry>
	<Entry>
		<zType>TEXT_JUKEBOX_MUSIC_TRACK_SKIP_HOVER</zType>
		<de-DE>Include this track in the playlist.</de-DE>
	</Entry>
	<Entry>
		<zType>TEXT_UI_STREAMING_LICENSED_WARNING_TITLE</zType>
		<de-DE>Video Creators / LiveStreamers</de-DE>
	</Entry>
	<Entry>
		<zType>TEXT_UI_STREAMING_LICENSED_WARNING_BODY</zType>
		<de-DE>
Recording and Streaming Copyright Safety Mode is now enabled.

This will reduce issues when recording online videos and streams
by skipping any music tracks known to cause content protection 
flagging issues.
			
Warning: Online video sharing sites may still flag remaining 
music tracks and can prevent monetization of your videos. 
Streaming any music from the game is at your own risk.
		</de-DE>
	</Entry>
	<!-- Christopher Tin -->
	<Entry>
		<zType>TEXT_AUDIO_ARTIST_CHRISTOPHER_TIN</zType>
		<de-DE>Christopher Tin</de-DE>
	</Entry>
	<Entry>
		<zType>TEXT_AUDIO_MUSIC_BG_I_Lift_My_Eyes_feat_Abeer_Nehme</zType>
		<de-DE>I Lift My Eyes, Featuring Abeer Nehme</de-DE>
	</Entry>
	<Entry>
		<zType>TEXT_AUDIO_MUSIC_BG_The_Augur_Speaks__Rome</zType>
		<de-DE>The Augur Speaks (Rome)</de-DE>
	</Entry>
	<Entry>
		<zType>TEXT_AUDIO_MUSIC_BG_War_Elephant__Carthage</zType>
		<de-DE>War Elephant (Carthage)</de-DE>
	</Entry>
	<Entry>
		<zType>TEXT_AUDIO_MUSIC_BG_Festival_of_Dionysus__Greece</zType>
		<de-DE>Festival of Dionysus (Greece)</de-DE>
	</Entry>
	<Entry>
		<zType>TEXT_AUDIO_MUSIC_BG_The_Gardens__Babylon</zType>
		<de-DE>The Gardens (Babylon)</de-DE>
	</Entry>
	<Entry>
		<zType>TEXT_AUDIO_MUSIC_BG_Zealot_King__Assyria</zType>
		<de-DE>Zealot King (Assyria)</de-DE>
	</Entry>
	<Entry>
		<zType>TEXT_AUDIO_MUSIC_BG_Persepolis__Persia</zType>
		<de-DE>Persepolis (Persia)</de-DE>
	</Entry>
	<Entry>
		<zType>TEXT_AUDIO_MUSIC_BG_Trade_Routes__Egypt</zType>
		<de-DE>Trade Routes (Egypt)</de-DE>
	</Entry>
	<Entry>
		<zType>TEXT_AUDIO_MUSIC_BG_Tahmilah</zType>
		<de-DE>I Tahmilah (feat. Camille Feghali)</de-DE>
	</Entry>
	<Entry>
		<zType>TEXT_AUDIO_MUSIC_BG_Mawwal</zType>
		<de-DE>II Mawwal (feat. Meena Shamaly)</de-DE>
	</Entry>
	<Entry>
		<zType>TEXT_AUDIO_MUSIC_BG_Tarab_Pt__1</zType>
		<de-DE>III Tarab Pt. 1 (feat. Meena Shamaly)</de-DE>
	</Entry>
	<Entry>
		<zType>TEXT_AUDIO_MUSIC_BG_Tarab_Pt__2</zType>
		<de-DE>IV Tarab Pt. 2 (feat. Layal Watfeh)</de-DE>
	</Entry>
	<!-- music track names -->
	<Entry>
		<zType>TEXT_AUDIO_MUSIC_BG_3_PIECES_IN_OLD_STYLE___NO1</zType>
		<de-DE>3 Pieces in Old Style #1</de-DE>
	</Entry>
	<Entry>
		<zType>TEXT_AUDIO_MUSIC_BG_3_PIECES_IN_OLD_STYLE___NO3</zType>
		<de-DE>3 Pieces in Old Style #3</de-DE>
	</Entry>
	<Entry>
		<zType>TEXT_AUDIO_MUSIC_BG_AJAM_ON_BUZUK</zType>
		<de-DE>Ajam on Buzuk</de-DE>
	</Entry>
	<Entry>
		<zType>TEXT_AUDIO_MUSIC_BG_ANOUSH_GARUN__SWEET_SPRING_</zType>
		<de-DE>Anoush Garun (Sweet Spring)</de-DE>
	</Entry>
	<Entry>
		<zType>TEXT_AUDIO_MUSIC_BG_APARANI_PAR</zType>
		<de-DE>Aparani Par</de-DE>
	</Entry>
	<Entry>
		<zType>TEXT_AUDIO_MUSIC_BG_ARAVOT_LOUSABER__ASCENDING_LIGHT___ARR__KOMITAS____ARAVOT_LOUSABER__ASCENDING_LIGHT__</zType>
		<de-DE>Aravot lousaber (Ascending light)</de-DE>
	</Entry>
	<Entry>
		<zType>TEXT_AUDIO_MUSIC_BG_ARMENIAN_DANCE__ARR__K__NERCESIAN____ARMENIAN_DANCE</zType>
		<de-DE>Armenian Dance (K. Nercesian)</de-DE>
	</Entry>
	<Entry>
		<zType>TEXT_AUDIO_MUSIC_BG_ARTSAKHI_PAR</zType>
		<de-DE>Artsakhi par</de-DE>
	</Entry>
	<Entry>
		<zType>TEXT_AUDIO_MUSIC_BG_ASHKHARUMES_AKH_CHIM_KASHIL__I_WILL_NOT_BE_SAD_IN_THIS_WORLD__AS_LONG_AS_I_HAVE_YOU_</zType>
		<de-DE>Ashkharumes akh chim kashil (I will not be sad in this world, as long as I have you)</de-DE>
	</Entry>
	<Entry>
		<zType>TEXT_AUDIO_MUSIC_BG_AVE_MARIA_GRATIA_PLENA</zType>
		<de-DE>Ave Maria</de-DE>
	</Entry>
	<Entry>
		<zType>TEXT_AUDIO_MUSIC_BG_BOUDALI__SPIRIT_NAME</zType>
		<de-DE>Boudali (Spirit Name)</de-DE>
	</Entry>
	<Entry>
		<zType>TEXT_AUDIO_MUSIC_BG_EL_HAWZI__EL_HAWZI__EGYPT_</zType>
		<de-DE>El-hawzi (Egypt)</de-DE>
	</Entry>
	<Entry>
		<zType>TEXT_AUDIO_MUSIC_BG_ERVA_YES__I_AM_BURNED_BY_LOVE_</zType>
		<de-DE>Erva Yes - I Am Burned By Love</de-DE>
	</Entry>
	<Entry>
		<zType>TEXT_AUDIO_MUSIC_BG_EUNTES_IBANT_ET_FLEBANT___OP32</zType>
		<de-DE>Euntes Ibant et Flebant, Op. 32</de-DE>
	</Entry>
	<Entry>
		<zType>TEXT_AUDIO_MUSIC_BG_OPENING_GLASSWORKS</zType>
		<de-DE>Glassworks - Opening</de-DE>
	</Entry>
	<Entry>
		<zType>TEXT_AUDIO_MUSIC_BG_KATOT__LONGING_</zType>
		<de-DE>Katot (Longing)</de-DE>
	</Entry>
	<Entry>
		<zType>TEXT_AUDIO_MUSIC_BG_LA_ILLAH_ILLA_ALLAH</zType>
		<de-DE>La Ilaha Illa Allah</de-DE>
	</Entry>
	<Entry>
		<zType>TEXT_AUDIO_MUSIC_BG_LOBGESANG___OP72</zType>
		<de-DE>Lobgesang, Op. 72</de-DE>
	</Entry>
	<Entry>
		<zType>TEXT_AUDIO_MUSIC_BG_LUX_AURUMQUE__LIGHT_OF_GOLD_</zType>
		<de-DE>Lux Aurumque ("Light of Gold")</de-DE>
	</Entry>
	<Entry>
		<zType>TEXT_AUDIO_MUSIC_BG_MAWAL_GNAWI</zType>
		<de-DE>Mawal Gnawi</de-DE>
	</Entry>
	<!--<Entry>
		<zType>TEXT_AUDIO_MUSIC_BG_MISERERE___SWEEDISH_RADIO_CHOIR</zType>
		<de-DE>Miserere - Sweedish Radio Choir</de-DE>
	</Entry>-->
	<!-- Miserere Movements *************************************************** -->
	<Entry>
		<zType>TEXT_AUDIO_MUSIC_BG_MISERERE_MOVEMENT_1_MSTR</zType>
		<de-DE>Miserere - Movement 1</de-DE>
	</Entry>
	<Entry>
		<zType>TEXT_AUDIO_MUSIC_BG_MISERERE_MOVEMENT_3_MSTR</zType>
		<de-DE>Miserere - Movement 3</de-DE>
	</Entry>
	<Entry>
		<zType>TEXT_AUDIO_MUSIC_BG_MISERERE_MOVEMENT_4_MSTR</zType>
		<de-DE>Miserere - Movement 4</de-DE>
	</Entry>
	<Entry>
		<zType>TEXT_AUDIO_MUSIC_BG_MISERERE_MOVEMENT_5_MSTR</zType>
		<de-DE>Miserere - Movement 5</de-DE>
	</Entry>
	<Entry>
		<zType>TEXT_AUDIO_MUSIC_BG_MISERERE_MOVEMENT_6_MSTR</zType>
		<de-DE>Miserere - Movement 6</de-DE>
	</Entry>
	<Entry>
		<zType>TEXT_AUDIO_MUSIC_BG_MISERERE_MOVEMENT_7_MSTR</zType>
		<de-DE>Miserere - Movement 7</de-DE>
	</Entry>
	<Entry>
		<zType>TEXT_AUDIO_MUSIC_BG_MISERERE_MOVEMENT_9_MSTR</zType>
		<de-DE>Miserere - Movement 9</de-DE>
	</Entry>
	<Entry>
		<zType>TEXT_AUDIO_MUSIC_BG_MISERERE_MOVEMENT_11_MSTR</zType>
		<de-DE>Miserere - Movement 11</de-DE>
	</Entry>
	<!-- /Miserere Movements ************************************************** -->
	<Entry>
		<zType>TEXT_AUDIO_MUSIC_BG_MISSA_A_CAPPELLA___BENEDICTUS</zType>
		<de-DE>Missa a cappella - Benedictus</de-DE>
	</Entry>
	<Entry>
		<zType>TEXT_AUDIO_MUSIC_BG_MISSA_A_CAPPELLA___CREDO</zType>
		<de-DE>Missa a cappella - Credo</de-DE>
	</Entry>
	<Entry>
		<zType>TEXT_AUDIO_MUSIC_BG_MISSA_A_CAPPELLA___GLORIA</zType>
		<de-DE>Missa a cappella - Gloria</de-DE>
	</Entry>
	<Entry>
		<zType>TEXT_AUDIO_MUSIC_BG_MISSA_A_CAPPELLA___SANCTUS</zType>
		<de-DE>Missa a cappella - Sanctus</de-DE>
	</Entry>
	<Entry>
		<zType>TEXT_AUDIO_MUSIC_BG_MOME_MALENKO</zType>
		<de-DE>Mome Malenko</de-DE>
	</Entry>
	<Entry>
		<zType>TEXT_AUDIO_MUSIC_BG_OROVELA</zType>
		<de-DE>Orovela</de-DE>
	</Entry>
	<Entry>
		<zType>TEXT_AUDIO_MUSIC_BG_01_OUR_FATHER</zType>
		<de-DE>Our Father</de-DE>
	</Entry>
	<Entry>
		<zType>TEXT_AUDIO_MUSIC_BG_OV_ZARMANALI__WHAT_A_MIRACLE___ARR__KOMITAS____OV_ZARMANALI__WHAT_A_MIRACLE_</zType>
		<de-DE>Ov zarmanali (What a miracle) (arr. Komitas)</de-DE>
	</Entry>
	<Entry>
		<zType>TEXT_AUDIO_MUSIC_BG_03_TRI_PERSONAL_NATURE_OF_GOD</zType>
		<de-DE>Tri Personal Nature Of God</de-DE>
	</Entry>
	<Entry>
		<zType>TEXT_AUDIO_MUSIC_BG_05_PSALM_16</zType>
		<de-DE>Psalm 16</de-DE>
	</Entry>
	<Entry>
		<zType>TEXT_AUDIO_MUSIC_BG_02_PSALM_50</zType>
		<de-DE>Psalm 50</de-DE>
	</Entry>
	<Entry>
		<zType>TEXT_AUDIO_MUSIC_BG_06_PSALM_53</zType>
		<de-DE>Psalm 53</de-DE>
	</Entry>
	<Entry>
		<zType>TEXT_AUDIO_MUSIC_BG_IRAQ_RAQSAT_ALBEDOI__RAQSAT_ALBEDOI__IRAQ_</zType>
		<de-DE>Raqsat Albedoi - Iraq</de-DE>
	</Entry>
	<Entry>
		<zType>TEXT_AUDIO_MUSIC_BG_RASD</zType>
		<de-DE>Rasd (Syria)</de-DE>
	</Entry>
	<Entry>
		<zType>TEXT_AUDIO_MUSIC_BG_SANDIA</zType>
		<de-DE>Sandia</de-DE>
	</Entry>
	<Entry>
		<zType>TEXT_AUDIO_MUSIC_BG_SEV_ORER__DARK_DAYS_</zType>
		<de-DE>Sev Orer (Dark Days)</de-DE>
	</Entry>
	<Entry>
		<zType>TEXT_AUDIO_MUSIC_BG_SIRT_IM_SASANI__MY_HEART_IS_TREMBLING___ARR__V__KOMITAS____SIRT_IM_SASANI__MY_HEART_IS_TREMBLING_</zType>
		<de-DE>Sirt im sasani - My heart is trembling</de-DE>
	</Entry>
	<Entry>
		<zType>TEXT_AUDIO_MUSIC_BG_SLUNTSE</zType>
		<de-DE>Sluntse</de-DE>
	</Entry>
	<Entry>
		<zType>TEXT_AUDIO_MUSIC_BG_SPARMASETTA</zType>
		<de-DE>Sparmasetta</de-DE>
	</Entry>
	<Entry>
		<zType>TEXT_AUDIO_MUSIC_BG_TABAT___YA_HABIBI__TABAT__A_SONG_OF_PRAISE____YA_HABIBI__MY_BELOVED_</zType>
		<de-DE>Tabat - Ya Habibi: Tabat (A Song of Praise)</de-DE>
	</Entry>
	<Entry>
		<zType>TEXT_AUDIO_MUSIC_BG_TAQSIM_ON_NEY</zType>
		<de-DE>Taqsim on Ney</de-DE>
	</Entry>
	<Entry>
		<zType>TEXT_AUDIO_MUSIC_BG_TAQSIM_ON_VIOLIN</zType>
		<de-DE>Taqsim on Violin</de-DE>
	</Entry>
	<Entry>
		<zType>TEXT_AUDIO_MUSIC_BG_STANKA</zType>
		<de-DE>Stanka</de-DE>
	</Entry>
	<Entry>
		<zType>TEXT_AUDIO_MUSIC_BG_TOURA_TOURA</zType>
		<de-DE>Toura toura</de-DE>
	</Entry>
	<Entry>
		<zType>TEXT_AUDIO_MUSIC_BG_UD_IMPROVISATION_IN_MAKAM_HICAZ</zType>
		<de-DE>Ud improvisation in Makam Hicaz</de-DE>
	</Entry>
	<Entry>
		<zType>TEXT_AUDIO_MUSIC_BG_UNABI___MARALI___SHUSHIKI__MELODY_OF_DANCES___ARR__KOMITAS____UNABI___MARALI___SHUSHIKI__MELODY_OF_DANCES_</zType>
		<de-DE>Unabi - Marali - Shushiki (Melody of dances)</de-DE>
	</Entry>
	<Entry>
		<zType>TEXT_AUDIO_MUSIC_BG_VERKLARTE_NACHT__TRANSFIGURED_NIGHT_</zType>
		<de-DE>Verklärte Nacht (Transfigured Night)</de-DE>
	</Entry>
	<Entry>
		<zType>TEXT_AUDIO_MUSIC_BG_VIOLIN_CONCERTO___I</zType>
		<de-DE>Violin Concerto I</de-DE>
	</Entry>
	<Entry>
		<zType>TEXT_AUDIO_MUSIC_BG_VIOLIN_CONCERTO___II___PHILIP_GLASS</zType>
		<de-DE>Violin Concerto II</de-DE>
	</Entry>
	<Entry>
		<zType>TEXT_AUDIO_MUSIC_BG_VIOLIN_CONCERTO___III</zType>
		<de-DE>Violin Concerto III</de-DE>
	</Entry>
	<Entry>
		<zType>TEXT_AUDIO_MUSIC_BG_VOCH_ME_DZALEEG__THERE_IS_NO_FLOWER_</zType>
		<de-DE>Voch Me Dzaleeg (There is No Flower)</de-DE>
	</Entry>
	<Entry>
		<zType>TEXT_AUDIO_MUSIC_BG_YA_KHALIL__YA_KHALIL__NAME_OF_THE_BELOVED_</zType>
		<de-DE>Ya khalil (Name of the Beloved)</de-DE>
	</Entry>
	<Entry>
		<zType>TEXT_AUDIO_MUSIC_BG_YEKYALKS__WE_ARE_GATHERED_</zType>
		<de-DE>Yekyalks (We are gathered)</de-DE>
	</Entry>
	<Entry>
		<zType>TEXT_AUDIO_MUSIC_BG_YERAZ</zType>
		<de-DE>Yeraz</de-DE>
	</Entry>
	<Entry>
		<zType>TEXT_AUDIO_MUSIC_BG_ZABLEYALO_AGNE</zType>
		<de-DE>Zableyalo Agne</de-DE>
	</Entry>
	<Entry>
		<zType>TEXT_AUDIO_ARTIST_ALAN_SHAVARSH_BARDEZBANIAN</zType>
		<de-DE>Alan Shavarsh Bardezbanian</de-DE>
	</Entry>
	<Entry>
		<zType>TEXT_AUDIO_ARTIST_SERAPHIM_BIT_KHARIBI</zType>
		<de-DE>Seraphim Bit-Kharibi</de-DE>
	</Entry>
	<Entry>
		<zType>TEXT_AUDIO_ARTIST_NOUR_EDDINE</zType>
		<de-DE>Nour Eddine</de-DE>
	</Entry>
	<Entry>
		<zType>TEXT_AUDIO_ARTIST_HENRYK_GORECKI</zType>
		<de-DE>Henryk Gorecki</de-DE>
	</Entry>
	<Entry>
		<zType>TEXT_AUDIO_ARTIST_PHILIP_GLASS</zType>
		<de-DE>Philip Glass</de-DE>
	</Entry>
	<Entry>
		<zType>TEXT_AUDIO_ARTIST_LE_MYSTERE_DES_VOIX_BULGARES</zType>
		<de-DE>Le Mystere Des Voix Bulgares</de-DE>
	</Entry>
	<Entry>
		<zType>TEXT_AUDIO_ARTIST_EINOJUHANI_RAUTAVAARA</zType>
		<de-DE>Einojuhani Rautavaara</de-DE>
	</Entry>
	<Entry>
		<zType>TEXT_AUDIO_ARNOLD_SCHOENBERG</zType>
		<de-DE>Arnold Schoenberg</de-DE>
	</Entry>
	<Entry>
		<zType>TEXT_AUDIO_ARTIST_ERIC_WHITACRE</zType>
		<de-DE>Eric Whitacre</de-DE>
	</Entry>
	<Entry>
		<zType>TEXT_AUDIO_ARTIST_BULGARIAN_STATE</zType>
		<de-DE>Bulgarian State Television Female Choir</de-DE>
	</Entry>
	<Entry>
		<zType>TEXT_AUDIO_ARTIST_SALMA_AL_ASSAL</zType>
		<de-DE>Salma Al Assal and others</de-DE>
	</Entry>
	<Entry>
		<zType>TEXT_AUDIO_ARTIST_HOVHAN_MANDAKOUNI</zType>
		<de-DE>Hovhan Mandakouni</de-DE>
	</Entry>
	<Entry>
		<zType>TEXT_AUDIO_ARTIST_MUHAMMAD_ABDUL_KARIM</zType>
		<de-DE>Muhammad Abdul Karim</de-DE>
	</Entry>
	<Entry>
		<zType>TEXT_AUDIO_ARTIST_DANIEL_GAZARIAN</zType>
		<de-DE>Daniel Gazarian</de-DE>
	</Entry>
	<Entry>
		<zType>TEXT_AUDIO_ARTIST_SHOGHAKEN_FOLK_ENSEMBLE</zType>
		<de-DE>Shoghaken Folk Ensemble</de-DE>
	</Entry>
	<Entry>
		<zType>TEXT_AUDIO_ARTIST_HAISSMAVOURK_CHOIR</zType>
		<de-DE>Haissmavourk Choir</de-DE>
	</Entry>
	<Entry>
		<zType>TEXT_AUDIO_ARTIST_KHACHATUR_NERCESIAN</zType>
		<de-DE>Khachatur Nercesian</de-DE>
	</Entry>
	<Entry>
		<zType>TEXT_AUDIO_ARTIST_HOSSAM_RAMZY</zType>
		<de-DE>Hossam Ramzy</de-DE>
	</Entry>
	<Entry>
		<zType>TEXT_AUDIO_ARTIST_HARUTIAN_HARUTIUNIAN</zType>
		<de-DE>Harutiun Harutiunian</de-DE>
	</Entry>
	<Entry>
		<zType>TEXT_AUDIO_ARTIST_KAVKASIA_TRIO</zType>
		<de-DE>Kavkasia Trio</de-DE>
	</Entry>
	<Entry>
		<zType>TEXT_AUDIO_ARTIST_AMED_MUKHTAR</zType>
		<de-DE>Ahmed Mukhtar</de-DE>
	</Entry>
	<Entry>
		<zType>TEXT_AUDIO_ARTIST_AARAKEL_SIUNETSI</zType>
		<de-DE>Arakel Siunetsi</de-DE>
	</Entry>
	<Entry>
		<zType>TEXT_AUDIO_ARTIST_BEDRUDIN_HALIBIE</zType>
		<de-DE>Bedrudin Halibie</de-DE>
	</Entry>
	<Entry>
		<zType>TEXT_AUDIO_ARTIST_SUFI_MUSIC_ENSEMBLE</zType>
		<de-DE>Sufi Music Ensemble</de-DE>
	</Entry>
	<Entry>
		<zType>TEXT_AUDIO_ARTIST_KOMITAS_VARDAPET</zType>
		<de-DE>Komitas Vardapet</de-DE>
	</Entry>
	<!-- MUSICBED ************************************************************* -->
	<Entry>
		<zType>TEXT_AUDIO_MUSIC_BG_ASCENT___CATHEDRAL</zType>
		<de-DE>Ascent</de-DE>
	</Entry>
	<Entry>
		<zType>TEXT_AUDIO_MUSIC_BG_BEAUTY_MARK___CHAD_LAWSON</zType>
		<de-DE>Beauty Mark</de-DE>
	</Entry>
	<Entry>
		<zType>TEXT_AUDIO_MUSIC_BG_BELLY_OF_THE_WHALE___SONGS_OF_WATER</zType>
		<de-DE>Belly of the Whale</de-DE>
	</Entry>
	<Entry>
		<zType>TEXT_AUDIO_MUSIC_BG_CLOUDS__NOT_CLOCKS___SLOW_MEADOW</zType>
		<de-DE>Clouds, Not Clocks</de-DE>
	</Entry>
	<Entry>
		<zType>TEXT_AUDIO_MUSIC_BG_CREATING_LIFE___DEXTER_BRITAIN</zType>
		<de-DE>Creating Life</de-DE>
	</Entry>
	<Entry>
		<zType>TEXT_AUDIO_MUSIC_BG_D_S___ALISTAIR_SUNG</zType>
		<de-DE>D.S</de-DE>
	</Entry>
	<Entry>
		<zType>TEXT_AUDIO_MUSIC_BG_DARK_TRAVELS___ALISTAIR_SUNG</zType>
		<de-DE>Dark Travels</de-DE>
	</Entry>
	<Entry>
		<zType>TEXT_AUDIO_MUSIC_BG_DAYDREAM_IN_D_FOR_CELLO___ERIC_KINNY</zType>
		<de-DE>Daydream in D for Cello</de-DE>
	</Entry>
	<Entry>
		<zType>TEXT_AUDIO_MUSIC_BG_DEEPER___CHRIS_COLEMAN</zType>
		<de-DE>Deeper</de-DE>
	</Entry>
	<Entry>
		<zType>TEXT_AUDIO_MUSIC_BG_DEEPER__EXTENDED_VERSION____CHRIS_COLEMAN</zType>
		<de-DE>Deeper (Extended Version)</de-DE>
	</Entry>
	<Entry>
		<zType>TEXT_AUDIO_MUSIC_BG_DIRECTIONS___STEVEN_GUTHEINZ</zType>
		<de-DE>Directions</de-DE>
	</Entry>
	<Entry>
		<zType>TEXT_AUDIO_MUSIC_BG_DON_T_GO___CHRIS_COLEMAN</zType>
		<de-DE>Don't Go</de-DE>
	</Entry>
	<Entry>
		<zType>TEXT_AUDIO_MUSIC_BG_ELEGY___DEXTER_BRITAIN</zType>
		<de-DE>Elegy</de-DE>
	</Entry>
	<Entry>
		<zType>TEXT_AUDIO_MUSIC_BG_FALLING_OCEAN___CHAD_LAWSON</zType>
		<de-DE>Falling Ocean</de-DE>
	</Entry>
	<Entry>
		<zType>TEXT_AUDIO_MUSIC_BG_FOR_HER_FEAT__PHILIP_DANIEL__SOLO_STRINGS____SHAWN_WILLIAMS</zType>
		<de-DE>For Her feat. Philip Daniel (Solo Strings)</de-DE>
	</Entry>
	<Entry>
		<zType>TEXT_AUDIO_MUSIC_BG_FOR_KATHERINE__WITH_PETER_CAVALLO____KYLE_MCEVOY</zType>
		<de-DE>For Katherine (with Peter Cavallo)</de-DE>
	</Entry>
	<Entry>
		<zType>TEXT_AUDIO_MUSIC_BG_GOLESTAN___MAX_LL</zType>
		<de-DE>Golestan</de-DE>
	</Entry>
	<Entry>
		<zType>TEXT_AUDIO_MUSIC_BG_IN_THE_END___FUTURE_OF_FORESTRY</zType>
		<de-DE>In the End</de-DE>
	</Entry>
	<Entry>
		<zType>TEXT_AUDIO_MUSIC_BG_IRIS___TOPU</zType>
		<de-DE>Iris</de-DE>
	</Entry>
	<Entry>
		<zType>TEXT_AUDIO_MUSIC_BG_LET___GRACIE_AND_RACHEL</zType>
		<de-DE>Let</de-DE>
	</Entry>
	<Entry>
		<zType>TEXT_AUDIO_MUSIC_BG_LITTLE___KINGPINGUIN</zType>
		<de-DE>Little</de-DE>
	</Entry>
	<Entry>
		<zType>TEXT_AUDIO_MUSIC_BG_MY_HARP___FUTURE_OF_FORESTRY</zType>
		<de-DE>My Harp</de-DE>
	</Entry>
	<Entry>
		<zType>TEXT_AUDIO_MUSIC_BG_NEW_BEGINNINGS___ALISTAIR_SUNG</zType>
		<de-DE>New Beginnings</de-DE>
	</Entry>
	<Entry>
		<zType>TEXT_AUDIO_MUSIC_BG_O_HAPPY_FAULT___AUDREY_ASSAD</zType>
		<de-DE>O Happy Fault</de-DE>
	</Entry>
	<Entry>
		<zType>TEXT_AUDIO_MUSIC_BG_POOL___STEVEN_GUTHEINZ</zType>
		<de-DE>Pool</de-DE>
	</Entry>
	<Entry>
		<zType>TEXT_AUDIO_MUSIC_BG_SANDSTONE___BLAKE_EWING</zType>
		<de-DE>Sandstone</de-DE>
	</Entry>
	<Entry>
		<zType>TEXT_AUDIO_MUSIC_BG_SEARCHING_THE_UNKNOWN___ALISTAIR_SUNG</zType>
		<de-DE>Searching The Unknown</de-DE>
	</Entry>
	<Entry>
		<zType>TEXT_AUDIO_MUSIC_BG_SECRETS_OF_SILK___MAX_LL</zType>
		<de-DE>Secrets of Silk</de-DE>
	</Entry>
	<Entry>
		<zType>TEXT_AUDIO_MUSIC_BG_SOMETIMES___STEVEN_GUTHEINZ</zType>
		<de-DE>Sometimes</de-DE>
	</Entry>
	<Entry>
		<zType>TEXT_AUDIO_MUSIC_BG_SUMMER___CATHEDRAL</zType>
		<de-DE>Summer</de-DE>
	</Entry>
	<Entry>
		<zType>TEXT_AUDIO_MUSIC_BG_THE_FRAGILE_PART___AJ_HOCHHALTER</zType>
		<de-DE>The Fragile Part</de-DE>
	</Entry>
	<Entry>
		<zType>TEXT_AUDIO_MUSIC_BG_TORRID__PIANO___PADS_ONLY____BRADFORD_NYGHT</zType>
		<de-DE>Torrid (Piano and Pads Only)</de-DE>
	</Entry>
	<Entry>
		<zType>TEXT_AUDIO_MUSIC_BG_TOUCH___CHAD_LAWSON</zType>
		<de-DE>Touch</de-DE>
	</Entry>
	<Entry>
		<zType>TEXT_AUDIO_MUSIC_BG_UNEARTHED_FEAT__PHILIP_DANIEL__SOLO_STRINGS____SHAWN_WILLIAMS</zType>
		<de-DE>Unearthed feat. Philip Daniel (Solo Strings)</de-DE>
	</Entry>
	<Entry>
		<zType>TEXT_AUDIO_MUSIC_BG_UNION___TOLO</zType>
		<de-DE>Union</de-DE>
	</Entry>
	<Entry>
		<zType>TEXT_AUDIO_MUSIC_BG_VOWS_ON_THE_HILLSIDE___TIMBRE</zType>
		<de-DE>Vows on the Hillside</de-DE>
	</Entry>
	<Entry>
		<zType>TEXT_AUDIO_MUSIC_BG_WADING___ALISTAIR_SUNG</zType>
		<de-DE>Wading</de-DE>
	</Entry>
	<Entry>
		<zType>TEXT_AUDIO_MUSIC_BG_YULE___KINO</zType>
		<de-DE>Yule</de-DE>
	</Entry>
	<!-- /MUSICBED ************************************************************ -->
	<!-- MUSICBED ARTISTS ***************************************************** -->
	<Entry>
		<zType>TEXT_AUDIO_ARTIST_CATHEDRAL</zType>
		<de-DE>Cathedral</de-DE>
	</Entry>
	<Entry>
		<zType>TEXT_AUDIO_ARTIST_CHAD_LAWSON</zType>
		<de-DE>Chad Lawson</de-DE>
	</Entry>
	<Entry>
		<zType>TEXT_AUDIO_ARTIST_SONGS_OF_WATER</zType>
		<de-DE>Songs Of Water</de-DE>
	</Entry>
	<Entry>
		<zType>TEXT_AUDIO_ARTIST_SLOW_MEADOW</zType>
		<de-DE>Slow Meadow</de-DE>
	</Entry>
	<Entry>
		<zType>TEXT_AUDIO_ARTIST_DEXTER_BRITAIN</zType>
		<de-DE>Dexter Britain</de-DE>
	</Entry>
	<Entry>
		<zType>TEXT_AUDIO_ARTIST_ALISTAIR_SUNG</zType>
		<de-DE>Alistair Sung</de-DE>
	</Entry>
	<Entry>
		<zType>TEXT_AUDIO_ARTIST_ERIC_KINNY</zType>
		<de-DE>Eric Kinny</de-DE>
	</Entry>
	<Entry>
		<zType>TEXT_AUDIO_ARTIST_CHRIS_COLEMAN</zType>
		<de-DE>Chris Coleman</de-DE>
	</Entry>
	<Entry>
		<zType>TEXT_AUDIO_ARTIST_STEVEN_GUTHEINZ</zType>
		<de-DE>Steven Gutheinz</de-DE>
	</Entry>
	<Entry>
		<zType>TEXT_AUDIO_ARTIST_SHAWN_WILLIAMS</zType>
		<de-DE>Shawn Williams</de-DE>
	</Entry>
	<Entry>
		<zType>TEXT_AUDIO_ARTIST_KYLE_MCEVOY</zType>
		<de-DE>Kyle Mcevoy</de-DE>
	</Entry>
	<Entry>
		<zType>TEXT_AUDIO_ARTIST_MAX_LL</zType>
		<de-DE>Max LL</de-DE>
	</Entry>
	<Entry>
		<zType>TEXT_AUDIO_ARTIST_FUTURE_OF_FORESTRY</zType>
		<de-DE>Future Of Forestry</de-DE>
	</Entry>
	<Entry>
		<zType>TEXT_AUDIO_ARTIST_TOPU</zType>
		<de-DE>Topu</de-DE>
	</Entry>
	<Entry>
		<zType>TEXT_AUDIO_ARTIST_GRACIE_AND_RACHEL</zType>
		<de-DE>Gracie <![CDATA[&]]> Rachel</de-DE>
	</Entry>
	<Entry>
		<zType>TEXT_AUDIO_ARTIST_KINGPINGUIN</zType>
		<de-DE>Kingpinguin</de-DE>
	</Entry>
	<Entry>
		<zType>TEXT_AUDIO_ARTIST_AUDREY_ASSAD</zType>
		<de-DE>Audrey Assad</de-DE>
	</Entry>
	<Entry>
		<zType>TEXT_AUDIO_ARTIST_BLAKE_EWING</zType>
		<de-DE>Blake Ewing</de-DE>
	</Entry>
	<Entry>
		<zType>TEXT_AUDIO_ARTIST_AJ_HOCHHALTER</zType>
		<de-DE>Aj Hochhalter</de-DE>
	</Entry>
	<Entry>
		<zType>TEXT_AUDIO_ARTIST_BRADFORD_NYGHT</zType>
		<de-DE>Bradford Nyght</de-DE>
	</Entry>
	<Entry>
		<zType>TEXT_AUDIO_ARTIST_TOLO</zType>
		<de-DE>Tolo</de-DE>
	</Entry>
	<Entry>
		<zType>TEXT_AUDIO_ARTIST_TIMBRE</zType>
		<de-DE>Timbre</de-DE>
	</Entry>
	<Entry>
		<zType>TEXT_AUDIO_ARTIST_KINO</zType>
		<de-DE>Kino</de-DE>
	</Entry>
	<!-- /MUSICBED ARTISTS***************************************************** -->
	<!-- SCHUBERT MUSIC PUBLISHING ******************************************** -->
	<Entry>
		<zType>TEXT_AUDIO_MUSIC_BG_ATMADJA_DUMA_STRACHILU</zType>
		<de-DE>Atmadja Duma Strachilu</de-DE>
	</Entry>
	<Entry>
		<zType>TEXT_AUDIO_MUSIC_BG_DRAGANA_I_SLAVEI</zType>
		<de-DE>Dragana I Slavei</de-DE>
	</Entry>
	<Entry>
		<zType>TEXT_AUDIO_MUSIC_BG_EI_MORI_ROUJKE</zType>
		<de-DE>Ei Mori Roujke</de-DE>
	</Entry>
	<Entry>
		<zType>TEXT_AUDIO_MUSIC_BG_ERGHEN_DIADO</zType>
		<de-DE>Erghen Diado</de-DE>
	</Entry>
	<Entry>
		<zType>TEXT_AUDIO_MUSIC_BG_KALIMANKOU_DENKOU</zType>
		<de-DE>Kalimankou Denkou</de-DE>
	</Entry>
	<Entry>
		<zType>TEXT_AUDIO_MUSIC_BG_MESSETSCHINKO_LIO_GREILIVKO</zType>
		<de-DE>Messetschinko Lio Greilivko</de-DE>
	</Entry>
	<Entry>
		<zType>TEXT_AUDIO_MUSIC_BG_MIR_STANKE_LE</zType>
		<de-DE>Mir Stanke Le</de-DE>
	</Entry>
	<Entry>
		<zType>TEXT_AUDIO_MUSIC_BG_PILENTZE_PEE</zType>
		<de-DE>Pilentze Pee</de-DE>
	</Entry>
	<Entry>
		<zType>TEXT_AUDIO_MUSIC_BG_POLEGNALA_E_TODORA</zType>
		<de-DE>Polegnala E Todora</de-DE>
	</Entry>
	<Entry>
		<zType>TEXT_AUDIO_MUSIC_BG_PRITOURITZE_PLANINATA</zType>
		<de-DE>Pritouritze Planinata</de-DE>
	</Entry>
	<Entry>
		<zType>TEXT_AUDIO_MUSIC_BG_SHOPE__SHOPE</zType>
		<de-DE>Shope  Shope</de-DE>
	</Entry>
	<Entry>
		<zType>TEXT_AUDIO_MUSIC_BG_STRATI_NA_ANGELAKI_DOUMASCHE</zType>
		<de-DE>Strati Na Angelaki Doumasche</de-DE>
	</Entry>
	<!-- /SCHUBERT MUSIC PUBLISHING ******************************************* -->
	<!-- CAPELLA ROMANA ******************************************************* -->
	<!-- SONGS ******************************************** -->
	<Entry>
		<zType>TEXT_AUDIO_MUSIC_BG_EVENING_HYMN</zType>
		<de-DE>Evening Hymn (“Phos hilaron”)</de-DE>
	</Entry>
	<Entry>
		<zType>TEXT_AUDIO_MUSIC_BG_LAMENTATIO_SANCT___MATRIS_ECCLESI___CONSTANTINOPOLITAN</zType>
		<de-DE>Lamentatio Sanctæ Matris Ecclesiæ Constantinopolitanæ</de-DE>
	</Entry>
	<Entry>
		<zType>TEXT_AUDIO_MUSIC_BG_CUM_AUTEM_VENISSENT</zType>
		<de-DE>Cum Autem Venissent</de-DE>
	</Entry>
	<Entry>
		<zType>TEXT_AUDIO_MUSIC_BG_HIERARCHICAL_ENTRANCE_RITE_FOR_A_BYZANTINE_DIVINE_LITURGY_KONTAKION_OF_THE_MOTHER_OF_GOD__MODE_PLAGAL_4_</zType>
		<de-DE>Hierarchical Entrance Rite for a Byzantine Divine Liturgy: Kontakion of the Mother of God (Mode Plagal 4)</de-DE>
	</Entry>
	<Entry>
		<zType>TEXT_AUDIO_MUSIC_BG_ALLELUIARION_FOR_CHRISTMAS_DAY</zType>
		<de-DE>Alleluiarion for Christmas Day</de-DE>
	</Entry>
	<Entry>
		<zType>TEXT_AUDIO_MUSIC_BG_ANTIPHON_7_VERSES</zType>
		<de-DE>Antiphon 7 Verses</de-DE>
	</Entry>
	<Entry>
		<zType>TEXT_AUDIO_MUSIC_BG_WHEN_THE_GLORIOUS_DISCIPLES</zType>
		<de-DE>When the glorious disciples</de-DE>
	</Entry>
	<Entry>
		<zType>TEXT_AUDIO_MUSIC_BG_VASILISSA_ERGO_GAUDE</zType>
		<de-DE>Vasilissa ergo gaude</de-DE>
	</Entry>
	<Entry>
		<zType>TEXT_AUDIO_MUSIC_BG_VESPERS_ANTIPHON</zType>
		<de-DE>Vespers Antiphon</de-DE>
	</Entry>
	<Entry>
		<zType>TEXT_AUDIO_MUSIC_BG_YOUR_BRIDAL_CHAMBER</zType>
		<de-DE>Your bridal chamber</de-DE>
	</Entry>
	<Entry>
		<zType>TEXT_AUDIO_MUSIC_BG_SEPULTO_DOMINO</zType>
		<de-DE>Sepulto Domino</de-DE>
	</Entry>
	<Entry>
		<zType>TEXT_AUDIO_MUSIC_BG_LET_ALL_MORTAL_FLESH_KEEP_SILENCE</zType>
		<de-DE>Let all mortal flesh keep silence</de-DE>
	</Entry>
	<Entry>
		<zType>TEXT_AUDIO_MUSIC_BG_O_DULCISSIME</zType>
		<de-DE>O Dulcissime</de-DE>
	</Entry>
	<Entry>
		<zType>TEXT_AUDIO_MUSIC_BG_PASSION_STICHERON___GAZES___TRADITIONAL</zType>
		<de-DE>Passion Sticheron - Gazes and Traditional</de-DE>
	</Entry>
	<Entry>
		<zType>TEXT_AUDIO_MUSIC_BG_SEQUENCE</zType>
		<de-DE>Sequence</de-DE>
	</Entry>
	<Entry>
		<zType>TEXT_AUDIO_MUSIC_BG_THE_PARADISE_IN_EDEN</zType>
		<de-DE>The Paradise in Eden</de-DE>
	</Entry>
	<Entry>
		<zType>TEXT_AUDIO_MUSIC_BG_LIFT_UP_YOUR_GATES___GREEK</zType>
		<de-DE>Lift up your gates - Greek</de-DE>
	</Entry>
	<Entry>
		<zType>TEXT_AUDIO_MUSIC_BG_O_GREAT_PASCHA</zType>
		<de-DE>O Great Pascha</de-DE>
	</Entry>
	<Entry>
		<zType>TEXT_AUDIO_MUSIC_BG_OF_YOUR_MYSTICAL_SUPPER</zType>
		<de-DE>Of your mystical supper</de-DE>
	</Entry>
	<Entry>
		<zType>TEXT_AUDIO_MUSIC_BG_RULERS_OF_THE_PEOPLES___THEY_LAID_A_LAWLESS_CHARGE___LET_US_BRING_OUR_SENSES</zType>
		<de-DE>Rulers of the Peoples - They Laid a Lawless Charge - Let Us Bring Our Senses</de-DE>
	</Entry>
	<Entry>
		<zType>TEXT_AUDIO_MUSIC_BG_THE_WISE_THIEF</zType>
		<de-DE>The Wise Thief</de-DE>
	</Entry>
	<Entry>
		<zType>TEXT_AUDIO_MUSIC_BG_KONTAKION_OF_THE_CROSS</zType>
		<de-DE>Kontakion of the Cross</de-DE>
	</Entry>
	<!-- /SONGS ******************************************* -->
	<!-- ARTISTS ****************************************** -->
	<Entry>
		<zType>TEXT_AUDIO_ARTIST_CAPPELLA_ROMANA__ALEXANDER_LINGAS</zType>
		<de-DE>Cappella Romana; Alexander Lingas</de-DE>
	</Entry>
	<Entry>
		<zType>TEXT_AUDIO_ARTIST_CAPPELLA_ROMANA__ALEXANDER_LINGAS__AARON_CAIN__MARK_POWELL</zType>
		<de-DE>Cappella Romana; Alexander Lingas; Aaron Cain; Mark Powell</de-DE>
	</Entry>

	<Entry>
		<zType>TEXT_AUDIO_ARTIST_CAPPELLA_ROMANA</zType>
		<de-DE>Cappella Romana</de-DE>
	</Entry>
	<Entry>
		<zType>TEXT_AUDIO_ARTIST_CAPPELLA_ROMANA__ALEXANDER_LINGAS__SPYRIDON_ANTONOPOULOS__AARON_CAIN__MARK_POWELL</zType>
		<de-DE>Cappella Romana; Alexander Lingas; Spyridon Antonopoulos; Aaron Cain; Mark Powell</de-DE>
	</Entry>
	<Entry>
		<zType>TEXT_AUDIO_ARTIST_CAPPELLA_ROMANA__ALEXANDER_LINGAS__PHOTINI_DOWNIE_ROBINSON__KERRY_MCCARTHY</zType>
		<de-DE>Cappella Romana; Alexander Lingas; Photini Downie Robinson; Kerry McCarthy</de-DE>
	</Entry>
	<Entry>
		<zType>TEXT_AUDIO_ARTIST_CAPPELLA_ROMANA__ALEXANDER_LINGAS__SPYRIDON_ANTONOPOULOS__JOHN_MICHAEL_BOYER</zType>
		<de-DE>Cappella Romana; Alexander Lingas; Spyridon Antonopoulos; John Michael Boyer</de-DE>
	</Entry>
	<!-- /ARTISTS ***************************************** -->
	<!-- /CAPELLA ROMANA ****************************************************** -->
	<!-- Tobias Jackle ******************************************************** -->
	<!-- Songs ******************************************** -->
	<Entry>
		<zType>TEXT_AUDIO_MUSIC_BG_EL_HELWA_DI</zType>
		<de-DE>El Helwa Di</de-DE>
	</Entry>
	<Entry>
		<zType>TEXT_AUDIO_MUSIC_BG_KING_OF_KINGS</zType>
		<de-DE>King of Kings</de-DE>
	</Entry>
	<Entry>
		<zType>TEXT_AUDIO_MUSIC_BG_TWO_RIVERS</zType>
		<de-DE>Two Rivers</de-DE>
	</Entry>
	<!-- /Songs ******************************************* -->
	<!-- Artists ****************************************** -->
	<Entry>
		<zType>TEXT_AUDIO_ARTIST_TOBIAS_JACKLE__LEYLA_JOHNSON</zType>
		<de-DE>Tobias J<![CDATA[ä]]>ckle, Leyla Johnson</de-DE>
	</Entry>
	<Entry>
		<zType>TEXT_AUDIO_ARTIST_TOBIAS_JACKLE</zType>
		<de-DE>Tobias J<![CDATA[ä]]>ckle</de-DE>
	</Entry>
	<!-- /Artists ***************************************** -->
	<!-- /Tobias Jackle ******************************************************* -->
	<!-- Elie Hijaz Segments ************************************************** -->
	<!-- Songs ******************************************** -->
	<Entry>
		<zType>TEXT_AUDIO_MUSIC_BG_KAM_BOETHNA_MA_A_EL_NASEEM</zType>
		<de-DE>Kam Boethna ma'a El Naseem</de-DE>
	</Entry>
	<Entry>
		<zType>TEXT_AUDIO_MUSIC_BG_HIJAZ_TAQSIM_2</zType>
		<de-DE>Hijaz Taqsim 2</de-DE>
	</Entry>
	<Entry>
		<zType>TEXT_AUDIO_MUSIC_BG_FOUG_EL_NAKHEL</zType>
		<de-DE>Foug El Nakhel</de-DE>
	</Entry>
	<Entry>
		<zType>TEXT_AUDIO_MUSIC_BG_KADDOUKA_AL_MAYYAS___HALI_HAL</zType>
		<de-DE>kaddouka al mayyas / Hali Hal</de-DE>
	</Entry>
	<Entry>
		<zType>TEXT_AUDIO_MUSIC_BG_HIJAZ_TAQSIM_1</zType>
		<de-DE>Hijaz Taqsim 1</de-DE>
	</Entry>
	<Entry>
		<zType>TEXT_AUDIO_MUSIC_BG_TAQSIM_2</zType>
		<de-DE>Taqsim 2</de-DE>
	</Entry>
	<Entry>
		<zType>TEXT_AUDIO_MUSIC_BG_YA_KARAWAN</zType>
		<de-DE>Ya Karawan</de-DE>
	</Entry>
	<!-- /Songs ******************************************* -->
	<!-- Artists ****************************************** -->
	<Entry>
		<zType>TEXT_AUDIO_ARTIST_UMM_KULTHUM</zType>
		<de-DE>Umm Kulthum</de-DE>
	</Entry>
	<Entry>
		<zType>TEXT_AUDIO_ARTIST_ELIE_APOYAN</zType>
		<de-DE>Elie Apoyan</de-DE>
	</Entry>
	<Entry>
		<zType>TEXT_AUDIO_ARTIST_NAZEM_AL-GHAZAL</zType>
		<de-DE>Nazem al-Ghazal</de-DE>
	</Entry>
	<Entry>
		<zType>TEXT_AUDIO_ARTIST_SABAH_FAKHRY</zType>
		<de-DE>Sabah Fakhry</de-DE>
	</Entry>
	<!-- /Artists ***************************************** -->
	<!-- /Elie Hijaz Segments ************************************************** -->
	<!-- Elie Byzantine Chants************************************************** -->
	<!-- Songs ******************************************** -->
	<Entry>
		<zType>TEXT_AUDIO_MUSIC_BG_GREAT_COMPLINE</zType>
		<de-DE>Great Compline</de-DE>
	</Entry>
	<Entry>
		<zType>TEXT_AUDIO_MUSIC_BG_LORD_I_CALL__TONE_6_</zType>
		<de-DE>Lord I Call (Tone 6)</de-DE>
	</Entry>
	<Entry>
		<zType>TEXT_AUDIO_MUSIC_BG_IHMADOU_AL_RABBA___PSALM_117</zType>
		<de-DE>Ihmadou Al Rabba - PSALM 117</de-DE>
	</Entry>
	<Entry>
		<zType>TEXT_AUDIO_MUSIC_BG_AGNI_PARTHENE_IN_ARABIC</zType>
		<de-DE>Agni Parthene in Arabic</de-DE>
	</Entry>
	<Entry>
		<zType>TEXT_AUDIO_MUSIC_BG_AGNI_PARTHENE</zType>
		<de-DE>Agni Parthene</de-DE>
	</Entry>
	<Entry>
		<zType>TEXT_AUDIO_MUSIC_BG_SECOND_PART_OF_AGNI_PARTHENE</zType>
		<de-DE>Second Part of Agni Parthene</de-DE>
	</Entry>
	<Entry>
		<zType>TEXT_AUDIO_MUSIC_BG_PSALM_50_IN_ARAMAIC__HAVE_MERCY_ON_ME__O_GOD_</zType>
		<de-DE>Psalm 50 in Aramaic (Have Mercy on Me, O God)</de-DE>
	</Entry>
	<!-- /Songs ******************************************* -->
	<!-- Artists ****************************************** -->
	<Entry>
		<zType>TEXT_AUDIO_ARTIST_FATHER_AGHABIOS_ABOU_SAADAH</zType>
		<de-DE>Father Aghabios Abou Saadah</de-DE>
	</Entry>
	<Entry>
		<zType>TEXT_AUDIO_ARTIST_VASSILIS_HADJINICOLAOU</zType>
		<de-DE>Vassilis Hadjinicolaou</de-DE>
	</Entry>
	<Entry>
		<zType>TEXT_AUDIO_ARTIST_FATHER_NOULA_MALEK</zType>
		<de-DE>Father Noula Malek</de-DE>
	</Entry>
	<Entry>
		<zType>TEXT_AUDIO_ARTIST_FATHER_PETER_HANNA</zType>
		<de-DE>Father Peter Hanna</de-DE>
	</Entry>
	<Entry>
		<zType>TEXT_AUDIO_ARTIST_ST._NECTARIOS_OF_AEGINA</zType>
		<de-DE>St. Nectarios of Aegina</de-DE>
	</Entry>
	<Entry>
		<zType>TEXT_AUDIO_ARTIST_ARCHMANDITE_PANTELEIMON_FARAH</zType>
		<de-DE>Archmandite Panteleimon Farah</de-DE>
	</Entry>
	<Entry>
		<zType>TEXT_AUDIO_ARTIST_FATHER_SERAPHIM_BIT-KHARIBI</zType>
		<de-DE>Father Seraphim Bit-Kharibi</de-DE>
	</Entry>
	<!-- /Artists ***************************************** -->
	<!-- /Elie Byzantine Chants************************************************** -->

</Root>
